wwpdb/utils/wf/DataSelector.py
wwpdb/utils/wf/DataValueContainer.py
wwpdb/utils/wf/WfDataObject.py
wwpdb/utils/wf/__init__.py
wwpdb/utils/wf/dbapi/DbApiUtil.py
wwpdb/utils/wf/dbapi/DbCommand.py
wwpdb/utils/wf/dbapi/DbConnection.py
wwpdb/utils/wf/dbapi/LocalDbApi.py
wwpdb/utils/wf/dbapi/StatusDbApi.py
wwpdb/utils/wf/dbapi/WFEtime.py
wwpdb/utils/wf/dbapi/WfDbApi.py
wwpdb/utils/wf/dbapi/WfTracking.py
wwpdb/utils/wf/dbapi/__init__.py
wwpdb/utils/wf/dbapi/dbAPI.py
wwpdb/utils/wf/plugins/AnnotationUtils.py
wwpdb/utils/wf/plugins/ChemCompUtils.py
wwpdb/utils/wf/plugins/DepositUtils.py
wwpdb/utils/wf/plugins/DictUtils.py
wwpdb/utils/wf/plugins/DpUtils.py
wwpdb/utils/wf/plugins/EmUtils.py
wwpdb/utils/wf/plugins/FileUtils.py
wwpdb/utils/wf/plugins/FormatUtils.py
wwpdb/utils/wf/plugins/NmrUtils.py
wwpdb/utils/wf/plugins/PcmCsvUtils.py
wwpdb/utils/wf/plugins/PdbxUtils.py
wwpdb/utils/wf/plugins/PrdSearchUtils.py
wwpdb/utils/wf/plugins/ReportUtils.py
wwpdb/utils/wf/plugins/SeqStatsUtils.py
wwpdb/utils/wf/plugins/SeqdbUtils.py
wwpdb/utils/wf/plugins/UtilsBase.py
wwpdb/utils/wf/plugins/ValidationUtils.py
wwpdb/utils/wf/plugins/__init__.py
wwpdb/utils/wf/process/ActionRegistry.py
wwpdb/utils/wf/process/ActionRegistryIo.py
wwpdb/utils/wf/process/ProcessRunner.py
wwpdb/utils/wf/process/__init__.py
wwpdb/utils/wf/schema/WfSchemaMap.py
wwpdb/utils/wf/schema/__init__.py
wwpdb/utils/wf/schema/database_descriptions.txt
wwpdb/utils/wf/schema/mandatory_items.txt
wwpdb_utils_wf-1.1.dist-info/METADATA
wwpdb_utils_wf-1.1.dist-info/WHEEL
wwpdb_utils_wf-1.1.dist-info/licenses/LICENSE
wwpdb_utils_wf-1.1.dist-info/RECORD
